{
    "user_2_course_2": {
        "inactiveTimeInSeconds": 758206,
        "lastChecked": 1736344835,
        "maxInactiveTime": 758206
    },
    "user_2_course_0": {
        "inactiveTimeInSeconds": 339216,
        "lastChecked": 1736120255,
        "maxInactiveTime": 339216
    },
    "user__course_0": {
        "inactiveTimeInSeconds": 31,
        "lastChecked": 1736118488,
        "maxInactiveTime": 31
    },
    "user__course_3": {
        "inactiveTimeInSeconds": 533,
        "lastChecked": 1736119046,
        "maxInactiveTime": 533
    },
    "user_2_course_3": {
        "inactiveTimeInSeconds": 434821,
        "lastChecked": 1736555158,
        "maxInactiveTime": 434821
    },
    "user_4_course_2": {
        "inactiveTimeInSeconds": 57658,
        "lastChecked": 1736270586,
        "maxInactiveTime": 57658
    },
    "user_5_course_2": {
        "inactiveTimeInSeconds": 57658,
        "lastChecked": 1736270587,
        "maxInactiveTime": 57658
    },
    "user_6_course_2": {
        "inactiveTimeInSeconds": 57658,
        "lastChecked": 1736270588,
        "maxInactiveTime": 57658
    },
    "user_7_course_2": {
        "inactiveTimeInSeconds": 57659,
        "lastChecked": 1736270589,
        "maxInactiveTime": 57659
    },
    "user_8_course_2": {
        "inactiveTimeInSeconds": 57659,
        "lastChecked": 1736270590,
        "maxInactiveTime": 57659
    }
}